Metadata-Version: 2.1
Name: behave-django-bse
Version: 1.4.0
Summary: Behave BDD integration for Django, temp fork until newer version is released...
Home-page: https://github.com/behave/behave-django
Author: Mitchel Cabuloy
Author-email: mixxorz@gmail.com
Maintainer: Peter Bittner, Javier Buzzi
Maintainer-email: django+SPAM@bittner.it
Project-URL: Documentation, https://behave-django.readthedocs.io/
Classifier: Development Status :: 5 - Production/Stable
Classifier: Environment :: Console
Classifier: Environment :: Plugins
Classifier: Environment :: Web Environment
Classifier: Framework :: Django
Classifier: Framework :: Django :: 3.2
Classifier: Framework :: Django :: 4.1
Classifier: Framework :: Django :: 4.2
Classifier: Intended Audience :: Developers
Classifier: License :: OSI Approved :: MIT License
Classifier: Operating System :: OS Independent
Classifier: Programming Language :: Python
Classifier: Programming Language :: Python :: 3
Classifier: Programming Language :: Python :: 3.6
Classifier: Programming Language :: Python :: 3.7
Classifier: Programming Language :: Python :: 3.8
Classifier: Programming Language :: Python :: 3.9
Classifier: Programming Language :: Python :: 3.10
Classifier: Programming Language :: Python :: 3.11
Classifier: Topic :: Internet :: WWW/HTTP
Classifier: Topic :: Internet :: WWW/HTTP :: Dynamic Content
Classifier: Topic :: Software Development :: Testing
License-File: LICENSE
License-File: AUTHORS.rst
Requires-Dist: beautifulsoup4
Requires-Dist: behave-bse[toml]
Requires-Dist: django >=3.2
